<?xml version="1.0" encoding="UTF-8"?>
<!--
    Document   : ejercicio_0001.xml
    Description:
        Estructura de grupos de epígrafes, epígrafes, cuentas y subcuentas del ejercicio 0001.
-->
<ejercicio>
   <cuenta_especial>
      <idcuentaesp>CAJA</idcuentaesp>
      <descripcion>Q3VlbnRhcyBkZSBjYWph</descripcion>
   </cuenta_especial>
   <cuenta_especial>
      <idcuentaesp>CAMNEG</idcuentaesp>
      <descripcion>Q3VlbnRhcyBkZSBkaWZlcmVuY2lhcyBuZWdhdGl2YXMgZGUgY2FtYmlv</descripcion>
   </cuenta_especial>
   <cuenta_especial>
      <idcuentaesp>CAMPOS</idcuentaesp>
      <descripcion>Q3VlbnRhcyBkZSBkaWZlcmVuY2lhcyBwb3NpdGl2YXMgZGUgY2FtYmlv</descripcion>
   </cuenta_especial>
   <cuenta_especial>
      <idcuentaesp>CLIENT</idcuentaesp>
      <descripcion>Q3VlbnRhcyBkZSBjbGllbnRlcw==</descripcion>
   </cuenta_especial>
   <cuenta_especial>
      <idcuentaesp>COMPRA</idcuentaesp>
      <descripcion>Q3VlbnRhcyBkZSBjb21wcmFz</descripcion>
   </cuenta_especial>
   <cuenta_especial>
      <idcuentaesp>DEVCOM</idcuentaesp>
      <descripcion>RGV2b2x1Y2lvbmVzIGRlIGNvbXByYXM=</descripcion>
   </cuenta_especial>
   <cuenta_especial>
      <idcuentaesp>DEVVEN</idcuentaesp>
      <descripcion>RGV2b2x1Y2lvbmVzIGRlIHZlbnRhcw==</descripcion>
   </cuenta_especial>
   <cuenta_especial>
      <idcuentaesp>DIVPOS</idcuentaesp>
      <descripcion>Q3VlbnRhcyBwb3IgZGlmZXJlbmNpYXMgcG9zaXRpdmFzIGVuIGRpdmlzYSBleHRyYW5qZXJh</descripcion>
   </cuenta_especial>
   <cuenta_especial>
      <idcuentaesp>EURNEG</idcuentaesp>
      <descripcion>Q3VlbnRhcyBwb3IgZGlmZXJlbmNpYXMgbmVnYXRpdmFzIGRlIGNvbnZlcnNpw7NuIGEgbGEgbW9uZWRhIGxvY2Fs</descripcion>
   </cuenta_especial>
   <cuenta_especial>
      <idcuentaesp>EURPOS</idcuentaesp>
      <descripcion>Q3VlbnRhcyBwb3IgZGlmZXJlbmNpYXMgcG9zaXRpdmFzIGRlIGNvbnZlcnNpw7NuIGEgbGEgbW9uZWRhIGxvY2Fs</descripcion>
   </cuenta_especial>
   <cuenta_especial>
      <idcuentaesp>GTORF</idcuentaesp>
      <descripcion>R2FzdG9zIHBvciByZWNhcmdvIGZpbmFuY2llcm8=</descripcion>
   </cuenta_especial>
   <cuenta_especial>
      <idcuentaesp>INGRF</idcuentaesp>
      <descripcion>SW5ncmVzb3MgcG9yIHJlY2FyZ28gZmluYW5jaWVybw==</descripcion>
   </cuenta_especial>
   <cuenta_especial>
      <idcuentaesp>IRPF</idcuentaesp>
      <descripcion>Q3VlbnRhcyBkZSByZXRlbmNpb25lcyBJUlBG</descripcion>
   </cuenta_especial>
   <cuenta_especial>
      <idcuentaesp>IRPFPR</idcuentaesp>
      <descripcion>Q3VlbnRhcyBkZSByZXRlbmNpb25lcyBwYXJhIHByb3ZlZWRvcmVzIElSUEZQUg==</descripcion>
   </cuenta_especial>
   <cuenta_especial>
      <idcuentaesp>IVAACR</idcuentaesp>
      <descripcion>Q3VlbnRhcyBhY3JlZWRvcmFzIGRlIElWQSBlbiBsYSByZWd1bGFyaXphY2nDs24=</descripcion>
   </cuenta_especial>
   <cuenta_especial>
      <idcuentaesp>IVADEU</idcuentaesp>
      <descripcion>Q3VlbnRhcyBkZXVkb3JhcyBkZSBJVkEgZW4gbGEgcmVndWxhcml6YWNpw7Nu</descripcion>
   </cuenta_especial>
   <cuenta_especial>
      <idcuentaesp>IVAEUE</idcuentaesp>
      <descripcion>Q3VlbnRhcyBkZSBJVkEgcmVwZXJjdXRpZG8gZW4gZW50cmVnYXMgaW50cmFjb211bml0YXJpYXM=</descripcion>
   </cuenta_especial>
   <cuenta_especial>
      <idcuentaesp>IVAREP</idcuentaesp>
      <descripcion>Q3VlbnRhcyBkZSBJVkEgcmVwZXJjdXRpZG8=</descripcion>
   </cuenta_especial>
   <cuenta_especial>
      <idcuentaesp>IVAREX</idcuentaesp>
      <descripcion>Q3VlbnRhcyBkZSBJVkEgcmVwZXJjdXRpZG8gcGFyYSBjbGllbnRlcyBleGVudG9zIGRlIElWQQ==</descripcion>
   </cuenta_especial>
   <cuenta_especial>
      <idcuentaesp>IVARUE</idcuentaesp>
      <descripcion>Q3VlbnRhcyBkZSBJVkEgcmVwZXJjdXRpZG8gZW4gYWRxdWlzaWNpb25lcyBpbnRyYWNvbXVuaXRhcmlhcw==</descripcion>
   </cuenta_especial>
   <cuenta_especial>
      <idcuentaesp>IVARXP</idcuentaesp>
      <descripcion>Q3VlbnRhcyBkZSBJVkEgcmVwZXJjdXRpZG8gZW4gZXhwb3J0YWNpb25lcw==</descripcion>
   </cuenta_especial>
   <cuenta_especial>
      <idcuentaesp>IVASIM</idcuentaesp>
      <descripcion>Q3VlbnRhcyBkZSBJVkEgc29wb3J0YWRvIGVuIGltcG9ydGFjaW9uZXM=</descripcion>
   </cuenta_especial>
   <cuenta_especial>
      <idcuentaesp>IVASOP</idcuentaesp>
      <descripcion>Q3VlbnRhcyBkZSBJVkEgc29wb3J0YWRv</descripcion>
   </cuenta_especial>
   <cuenta_especial>
      <idcuentaesp>IVASUE</idcuentaesp>
      <descripcion>Q3VlbnRhcyBkZSBJVkEgc29wb3J0YWRvIGVuIGFkcXVpc2ljaW9uZXMgaW50cmFjb211bml0YXJpYXM=</descripcion>
   </cuenta_especial>
   <cuenta_especial>
      <idcuentaesp>PREVIO</idcuentaesp>
      <descripcion>Q3VlbnRhcyByZWxhdGl2YXMgYWwgZWplcmNpY2lvIHByZXZpbw==</descripcion>
   </cuenta_especial>
   <cuenta_especial>
      <idcuentaesp>PROVEE</idcuentaesp>
      <descripcion>Q3VlbnRhcyBkZSBwcm92ZWVkb3JlcyB5IGFjcmVlZG9yZXM=</descripcion>
   </cuenta_especial>
   <cuenta_especial>
      <idcuentaesp>PYG</idcuentaesp>
      <descripcion>UMOpcmRpZGFzIHkgZ2FuYW5jaWFz</descripcion>
   </cuenta_especial>
   <cuenta_especial>
      <idcuentaesp>VENTAS</idcuentaesp>
      <descripcion>Q3VlbnRhcyBkZSB2ZW50YXM=</descripcion>
   </cuenta_especial>
   <grupo_epigrafes>
      <codgrupo>1</codgrupo>
      <descripcion>QWN0aXZv</descripcion>
   </grupo_epigrafes>
   <grupo_epigrafes>
      <codgrupo>2</codgrupo>
      <descripcion>UGFzaXZv</descripcion>
   </grupo_epigrafes>
   <grupo_epigrafes>
      <codgrupo>3</codgrupo>
      <descripcion>Q2FwaXRhbA==</descripcion>
   </grupo_epigrafes>
   <grupo_epigrafes>
      <codgrupo>4</codgrupo>
      <descripcion>SW5ncmVzb3M=</descripcion>
   </grupo_epigrafes>
   <grupo_epigrafes>
      <codgrupo>5</codgrupo>
      <descripcion>Q29zdG9z</descripcion>
   </grupo_epigrafes>
   <grupo_epigrafes>
      <codgrupo>6</codgrupo>
      <descripcion>R2FzdG9z</descripcion>
   </grupo_epigrafes>
   <epigrafe>
      <codgrupo>1</codgrupo>
      <codepigrafe>100</codepigrafe>
      <descripcion>QWN0aXZv</descripcion>
   </epigrafe>
   <epigrafe>
      <codgrupo>2</codgrupo>
      <codepigrafe>200</codepigrafe>
      <descripcion>UGFzaXZv</descripcion>
   </epigrafe>
   <epigrafe>
      <codgrupo>3</codgrupo>
      <codepigrafe>300</codepigrafe>
      <descripcion>Q2FwaXRhbA==</descripcion>
   </epigrafe>
   <epigrafe>
      <codgrupo>4</codgrupo>
      <codepigrafe>400</codepigrafe>
      <descripcion>SW5ncmVzb3M=</descripcion>
   </epigrafe>
   <epigrafe>
      <codgrupo>5</codgrupo>
      <codepigrafe>500</codepigrafe>
      <descripcion>Q29zdG9z</descripcion>
   </epigrafe>
   <epigrafe>
      <codgrupo>6</codgrupo>
      <codepigrafe>600</codepigrafe>
      <descripcion>R2FzdG9z</descripcion>
   </epigrafe>
   <cuenta>
      <codepigrafe>100</codepigrafe>
      <codcuenta>1000</codcuenta>
      <descripcion>RWZlY3Rpdm8=</descripcion>
      <idcuentaesp/>
   </cuenta>
   <cuenta>
      <codepigrafe>100</codepigrafe>
      <codcuenta>10001</codcuenta>
      <descripcion>Q2FqYQ==</descripcion>
      <idcuentaesp/>
   </cuenta>
   <cuenta>
      <codepigrafe>100</codepigrafe>
      <codcuenta>10002</codcuenta>
      <descripcion>Q2FqYSBjaGljYQ==</descripcion>
      <idcuentaesp/>
   </cuenta>
   <cuenta>
      <codepigrafe>100</codepigrafe>
      <codcuenta>10003</codcuenta>
      <descripcion>QmFuY28gcG9wdWxhcg==</descripcion>
      <idcuentaesp/>
   </cuenta>
   <cuenta>
      <codepigrafe>100</codepigrafe>
      <codcuenta>10004</codcuenta>
      <descripcion>QmFucmVzZXJ2YXM=</descripcion>
      <idcuentaesp/>
   </cuenta>
   <cuenta>
      <codepigrafe>100</codepigrafe>
      <codcuenta>10005</codcuenta>
      <descripcion>QkhE</descripcion>
      <idcuentaesp/>
   </cuenta>
   <cuenta>
      <codepigrafe>100</codepigrafe>
      <codcuenta>1100</codcuenta>
      <descripcion>Q3VlbnRhcyBwb3IgY29icmFyIGNsaWVudGVz</descripcion>
      <idcuentaesp/>
   </cuenta>
   <cuenta>
      <codepigrafe>100</codepigrafe>
      <codcuenta>1200</codcuenta>
      <descripcion>Q3VlbnRhcyBwb3IgY29icmFyIGZ1bmNpb25hcmlvcyB5IGVtcGxlYWRvcw==</descripcion>
      <idcuentaesp/>
   </cuenta>
   <cuenta>
      <codepigrafe>100</codepigrafe>
      <codcuenta>1300</codcuenta>
      <descripcion>T3RyYXMgY3VlbnRhcyBwb3IgY29icmFy</descripcion>
      <idcuentaesp/>
   </cuenta>
   <cuenta>
      <codepigrafe>100</codepigrafe>
      <codcuenta>1400</codcuenta>
      <descripcion>SW52ZW50YXJpb3M=</descripcion>
      <idcuentaesp/>
   </cuenta>
   <cuenta>
      <codepigrafe>100</codepigrafe>
      <codcuenta>1500</codcuenta>
      <descripcion>R2FzdG9zIHBhZ2Fkb3MgcG9yIGFkZWxhbnRhZG8=</descripcion>
      <idcuentaesp/>
   </cuenta>
   <cuenta>
      <codepigrafe>100</codepigrafe>
      <codcuenta>1600</codcuenta>
      <descripcion>SW52ZXJzaW9uZXM=</descripcion>
      <idcuentaesp/>
   </cuenta>
   <cuenta>
      <codepigrafe>100</codepigrafe>
      <codcuenta>1700</codcuenta>
      <descripcion>UHJvcGllZGFkIHBsYW50YSB5IGVxdWlwbw==</descripcion>
      <idcuentaesp/>
   </cuenta>
   <cuenta>
      <codepigrafe>100</codepigrafe>
      <codcuenta>1800</codcuenta>
      <descripcion>QWN0aXZvcyBkaWZlcmlkb3M=</descripcion>
      <idcuentaesp/>
   </cuenta>
   <cuenta>
      <codepigrafe>100</codepigrafe>
      <codcuenta>1900</codcuenta>
      <descripcion>T3Ryb3MgYWN0aXZvcw==</descripcion>
      <idcuentaesp/>
   </cuenta>
   <cuenta>
      <codepigrafe>200</codepigrafe>
      <codcuenta>2000</codcuenta>
      <descripcion>RG9jdW1lbnRvcyBwb3IgcGFnYXI=</descripcion>
      <idcuentaesp/>
   </cuenta>
   <cuenta>
      <codepigrafe>200</codepigrafe>
      <codcuenta>2100</codcuenta>
      <descripcion>Q3VlbnRhcyBwb3IgcGFnYXIgcHJvdmVlZG9yZXM=</descripcion>
      <idcuentaesp/>
   </cuenta>
   <cuenta>
      <codepigrafe>200</codepigrafe>
      <codcuenta>2200</codcuenta>
      <descripcion>UmV0ZW5jaW9uZXMgeSBhY3VtdWxhY2lvbmVzIHBvciBwYWdhcg==</descripcion>
      <idcuentaesp/>
   </cuenta>
   <cuenta>
      <codepigrafe>200</codepigrafe>
      <codcuenta>2300</codcuenta>
      <descripcion>UGFzaXZvIGFsIGxhcmdvIHBsYXpv</descripcion>
      <idcuentaesp/>
   </cuenta>
   <cuenta>
      <codepigrafe>200</codepigrafe>
      <codcuenta>2400</codcuenta>
      <descripcion>T3Ryb3MgcGFzaXZvcw==</descripcion>
      <idcuentaesp/>
   </cuenta>
   <cuenta>
      <codepigrafe>300</codepigrafe>
      <codcuenta>30001</codcuenta>
      <descripcion>QWNjaW9uZXMgYXV0b3JpemFkYXM=</descripcion>
      <idcuentaesp/>
   </cuenta>
   <cuenta>
      <codepigrafe>300</codepigrafe>
      <codcuenta>30002</codcuenta>
      <descripcion>QWNjaW9uZXMgbm8gZW1pdGlkYXM=</descripcion>
      <idcuentaesp/>
   </cuenta>
   <cuenta>
      <codepigrafe>300</codepigrafe>
      <codcuenta>30003</codcuenta>
      <descripcion>UHJpbWEgZGUgYWNjaW9uZXMgY29tdW5lcw==</descripcion>
      <idcuentaesp/>
   </cuenta>
   <cuenta>
      <codepigrafe>300</codepigrafe>
      <codcuenta>30004</codcuenta>
      <descripcion>QWNjaW9uZXMgZW4gdGVzb3JlcsOtYQ==</descripcion>
      <idcuentaesp/>
   </cuenta>
   <cuenta>
      <codepigrafe>300</codepigrafe>
      <codcuenta>3100</codcuenta>
      <descripcion>UmVzZXJ2YXM=</descripcion>
      <idcuentaesp/>
   </cuenta>
   <cuenta>
      <codepigrafe>300</codepigrafe>
      <codcuenta>3200</codcuenta>
      <descripcion>UmVzdWx0YWRvcw==</descripcion>
      <idcuentaesp/>
   </cuenta>
   <cuenta>
      <codepigrafe>400</codepigrafe>
      <codcuenta>4100</codcuenta>
      <descripcion>VmVudGFz</descripcion>
      <idcuentaesp/>
   </cuenta>
   <cuenta>
      <codepigrafe>400</codepigrafe>
      <codcuenta>4200</codcuenta>
      <descripcion>U2VydmljaW9z</descripcion>
      <idcuentaesp/>
   </cuenta>
   <cuenta>
      <codepigrafe>400</codepigrafe>
      <codcuenta>4300</codcuenta>
      <descripcion>T3Ryb3MgaW5ncmVzb3M=</descripcion>
      <idcuentaesp/>
   </cuenta>
   <cuenta>
      <codepigrafe>400</codepigrafe>
      <codcuenta>4400</codcuenta>
      <descripcion>RGVzY3VlbnRvcyB5IGRldm9sdWNpb25lcw==</descripcion>
      <idcuentaesp/>
   </cuenta>
   <cuenta>
      <codepigrafe>500</codepigrafe>
      <codcuenta>5000</codcuenta>
      <descripcion>Q29zdG8gZGUgbGEgbWVyY2FuY8OtYSBjb21wcmFkYQ==</descripcion>
      <idcuentaesp/>
   </cuenta>
   <cuenta>
      <codepigrafe>600</codepigrafe>
      <codcuenta>6100</codcuenta>
      <descripcion>R2FzdG9zIGRlIG9wZXJhY2nDs24=</descripcion>
      <idcuentaesp/>
   </cuenta>
   <cuenta>
      <codepigrafe>600</codepigrafe>
      <codcuenta>6200</codcuenta>
      <descripcion>R2FzdG9zIGdlbmVyYWxlcyB5IGFkbWluaXN0cmF0aXZvcw==</descripcion>
      <idcuentaesp/>
   </cuenta>
   <cuenta>
      <codepigrafe>600</codepigrafe>
      <codcuenta>6300</codcuenta>
      <descripcion>R2FzdG9zIGZpbmFuY2llcm9z</descripcion>
      <idcuentaesp/>
   </cuenta>
   <subcuenta>
      <codcuenta>1000</codcuenta>
      <codsubcuenta>10001</codsubcuenta>
      <descripcion>Q2FqYQ==</descripcion>
      <coddivisa>USD</coddivisa>
   </subcuenta>
</ejercicio>
